django_solr/__init__.py
django_solr/admin.py
django_solr/apps.py
django_solr/models.py
django_solr/urls.py
django_solr/views.py
django_solr/django_solr/templates/index_list.html
django_solr/dsl/__init__.py
django_solr/dsl/backend.py
django_solr/dsl/exception.py
django_solr/dsl/fields.py
django_solr/dsl/indexes.py
django_solr/migrations/0001_initial.py
django_solr/migrations/__init__.py
django_solr/templates/admin/change_list.html
django_solr/templates/admin/django_solr/indexes/change_list.html
django_solr/templates/django_solr/index_list.html
django_solr_search-1.2.dist-info/METADATA
django_solr_search-1.2.dist-info/WHEEL
django_solr_search-1.2.dist-info/licenses/LICENSE
django_solr_search-1.2.dist-info/RECORD
